{
  "users": [
    {
      "email": "alexeydomut@gmail.com",
      "password": "111111As",
      "date": 1700992957516,
      "id": 1
    },
    {
      "email": "xeydomut@gmail.com",
      "password": "111111As",
      "date": 1700994301265,
      "id": 2
    },
    {
      "email": "eydomut@gmail.com",
      "password": "111111As",
      "date": 1700994640517,
      "id": 3
    },
    {
      "email": "alemut@gmail.com",
      "password": "111111As",
      "date": 1701194064802,
      "id": 4
    }
  ]
}